{"header":{"type":"esearch","version":"0.3"},"esearchresult":{"count":"40","retmax":"40","retstart":"0","idlist":["42092987","41665255","41175011","40944847","39827675","39052963","38576178","38356105","36528008","36435010","35844134","35582748","34218211","34155568","32717713","32221987","31675621","31571877","29908435","29414542","29153631","28856580","27649776","27988967","27146213","27608437","27589414","27335114","27221208","27217762","26666500","26471380","24512385","24717838","24446953","24256083","24116853","22813235","20592253","18341673"],"translationset":[],"querytranslation":"((\"brivaracetam\"[Title/Abstract] OR \"brivaracetam\"[All Fields] OR \"Briviact\"[Title/Abstract] OR \"Briviact\"[All Fields] OR \"UCB 34714\"[Title/Abstract] OR \"UCB 34714\"[All Fields]) AND (\"epilepsy\"[Title/Abstract] OR \"epilepsies\"[Title/Abstract] OR \"epileptic\"[Title/Abstract] OR \"seizure\"[Title/Abstract] OR \"seizures\"[Title/Abstract] OR \"infantile spasm\"[Title/Abstract] OR \"infantile spasms\"[Title/Abstract] OR \"lennox\"[Title/Abstract] OR \"dravet\"[Title/Abstract] OR \"status epilepticus\"[Title/Abstract]) AND (\"placebo\"[Title/Abstract] OR \"placebo-controlled\"[Title/Abstract] OR \"placebo-controlled\"[Title/Abstract]) AND (\"randomized\"[Title/Abstract] OR \"randomised\"[Title/Abstract] OR \"randomly\"[Title/Abstract] OR \"randomized controlled trial\"[Publication Type] OR \"random allocation\"[MeSH Terms] OR \"double-blind\"[Title/Abstract] OR \"double-blind\"[Title/Abstract]) AND (\"clinical trial\"[Publication Type] OR \"controlled clinical trial\"[Publication Type] OR \"randomized controlled trial\"[Publication Type] OR \"clinical trial, phase ii\"[Publication Type] OR \"clinical trial, phase iii\"[Publication Type] OR \"phase 2\"[Title/Abstract] OR \"phase II\"[Title/Abstract] OR \"phase 3\"[Title/Abstract] OR \"phase III\"[Title/Abstract] OR \"trial\"[Title/Abstract])) NOT (\"review\"[Publication Type] OR \"meta-analysis\"[Publication Type] OR \"systematic review\"[Publication Type])"}}
