{"header":{"type":"esearch","version":"0.3"},"esearchresult":{"count":"30","retmax":"30","retstart":"0","idlist":["41660750","40663783","36741623","36419530","33444208","28927402","23089176","20353411","17521343","17582922","16884455","16397976","15823510","15774213","11987312","11274308","10448830","10372564","9120451","9120226","8956916","8771597","8536677","7945002","7925148","8082624","8232945","1373372","1907907","1971862"],"translationset":[],"querytranslation":"((\"gabapentin\"[Title/Abstract] OR \"gabapentin\"[All Fields] OR \"Gralise\"[Title/Abstract] OR \"Gralise\"[All Fields] OR \"Horizant\"[Title/Abstract] OR \"Horizant\"[All Fields] OR \"Neurontin\"[Title/Abstract] OR \"Neurontin\"[All Fields]) AND (\"epilepsy\"[Title/Abstract] OR \"epileptic\"[Title/Abstract] OR \"seizure\"[Title/Abstract] OR \"seizures\"[Title/Abstract] OR \"infantile spasm\"[Title/Abstract] OR \"infantile spasms\"[Title/Abstract] OR \"lennox\"[Title/Abstract] OR \"dravet\"[Title/Abstract] OR \"status epilepticus\"[Title/Abstract]) AND (\"placebo\"[Title/Abstract] OR \"placebo-controlled\"[Title/Abstract] OR \"placebo-controlled\"[Title/Abstract]) AND (\"randomized\"[Title/Abstract] OR \"randomised\"[Title/Abstract] OR \"randomly\"[Title/Abstract] OR \"randomized controlled trial\"[Publication Type] OR \"random allocation\"[MeSH Terms] OR \"double-blind\"[Title/Abstract] OR \"double-blind\"[Title/Abstract]) AND (\"clinical trial\"[Publication Type] OR \"controlled clinical trial\"[Publication Type] OR \"randomized controlled trial\"[Publication Type] OR \"clinical trial, phase ii\"[Publication Type] OR \"clinical trial, phase iii\"[Publication Type] OR \"phase 2\"[Title/Abstract] OR \"phase II\"[Title/Abstract] OR \"phase 3\"[Title/Abstract] OR \"phase III\"[Title/Abstract] OR \"trial\"[Title/Abstract])) NOT (\"review\"[Publication Type] OR \"meta-analysis\"[Publication Type] OR \"systematic review\"[Publication Type])"}}
